cmdtools/__init__.py
cmdtools/base.py
cmdtools/callback/__init__.py
cmdtools/callback/base.py
cmdtools/callback/option.py
cmdtools/converter/__init__.py
cmdtools/converter/base.py
cmdtools/converter/converter.py
cmdtools/errors.py
cmdtools/ext/__init__.py
cmdtools/ext/command.py
cmdtools/ext/file.py
cmdtools/ext/param.py
cmdtools/utils/__init__.py
cmdtools/utils/string.py
cmdtools_py-3.1.0.dist-info/LICENSE
cmdtools_py-3.1.0.dist-info/METADATA
cmdtools_py-3.1.0.dist-info/WHEEL
cmdtools_py-3.1.0.dist-info/RECORD
