Metadata-Version: 2.3
Name: cmdtools-py
Version: 3.1.0
Summary: A (not quite) flexible command framework
License: MIT
Keywords: command-parser,command-processor,command,cmd,cmd-parser,framework,command-framework
Author: HugeBrain16
Author-email: hugebrain16@gmail.com
Maintainer: HugeBrain16
Maintainer-email: hugebrain16@gmail.com
Requires-Python: >=3.7
Classifier: Development Status :: 5 - Production/Stable
Classifier: Intended Audience :: Developers
Classifier: License :: OSI Approved :: MIT License
Classifier: Operating System :: OS Independent
Classifier: Programming Language :: Python :: 3
Classifier: Programming Language :: Python :: 3.7
Classifier: Programming Language :: Python :: 3.8
Classifier: Programming Language :: Python :: 3.9
Classifier: Programming Language :: Python :: 3.10
Classifier: Programming Language :: Python :: 3.11
Classifier: Programming Language :: Python :: 3.12
Classifier: Programming Language :: Python :: 3.13
Classifier: Programming Language :: Python :: 3 :: Only
Requires-Dist: typing-extensions (==4.7.1)
Project-URL: Documentation, https://cmdtools-py.readthedocs.io/en/latest
Project-URL: Issues Tracker, https://github.com/HugeBrain16/cmdtools/issues
Project-URL: Repository, https://github.com/HugeBrain16/cmdtools
